Workbook

Sheet Assumptions
A1: TCS – DCF VALUATION MODEL | Q2 FY2026 Data Sheet
A2: Key Assumptions & Historical Financials (INR Mn)
A3: HISTORICAL P&L (IFRS, INR Mn)
A4: Metric | B4: FY23 | C4: FY24 | D4: FY25 | E4: FY25 CAGR*
A5: Revenue (INR Mn) | B5: 2254580 | C5: 2408930 | D5: 2553240 | E5: =IFERROR((D5/B5)^(1/2)-1,0) -> 0.064174859
A6: Operating Income (EBIT) | B6: 621650 | C6: 593110 | D6: 621650 | E6: =IFERROR((D6/B6)^(1/2)-1,0) -> 0
A7: EBITDA | B7: 663530 | C7: 635440 | D7: 662540 | E7: =IFERROR((D7/B7)^(1/2)-1,0) -> -0.00074628845
A8: Net Profit | B8: 465850 | C8: 487970 | D8: 487760 | E8: =IFERROR((D8/B8)^(1/2)-1,0) -> 0.023245966
A9: Depreciation & Amort. | B9: 51530 | C9: 51530 | D9: 51530 | E9: =IFERROR((D9/B9)^(1/2)-1,0) -> 0
A10: Total Employees | B10: 592195 | C10: 601546 | D10: 613069 | E10: =IFERROR((D10/B10)^(1/2)-1,0) -> 0.017471633
A11: * CAGR = 2-year compound annual growth rate (FY23→FY25)
A13: DCF KEY ASSUMPTIONS (Blue = Input Cells)
A14: Assumption | B14: Value | C14: Notes
A15: Revenue Growth – Yr 1 (FY26E) | B15: 0.05 | C15: Moderating growth; CC guidance ~5%
A16: Revenue Growth – Yr 2 (FY27E) | B16: 0.07 | C16: Recovery as AI spend accelerates
A17: Revenue Growth – Yr 3 (FY28E) | B17: 0.09 | C17: Normalised growth trajectory
A18: Revenue Growth – Yr 4 (FY29E) | B18: 0.1 | C18: Sustained double-digit expansion
A19: Revenue Growth – Yr 5 (FY30E) | B19: 0.1 | C19: Steady state entry
A20: EBITDA Margin (avg, fy26-30) | B20: 0.26 | C20: Historical range 24-27%; conserv. 26%
A21: Capex as % Revenue | B21: 0.02 | C21: ~2% historically
A22: Tax Rate (effective) | B22: 0.26 | C22: ~25-26% effective rate
A23: Terminal Growth Rate (g) | B23: 0.05 | C23: Long-run India IT nominal growth
A24: WACC | B24: 0.105 | C24: Cost of equity ~11%; negligible debt
A25: Shares Outstanding (Mn) | B25: 3618 | C25: As per latest filing
A26: Net Cash / (Debt) (INR Mn) | B26: 450000 | C26: Cash + investments less debt

Sheet DCF Model
A1: TCS – DISCOUNTED CASH FLOW (DCF) VALUATION
A2: 5-Year FCF Projection | WACC Discount | Terminal Value | Intrinsic Value per Share
A3: Line Item | B3: FY25A | C3: FY26E | D3: FY27E | E3: FY28E | F3: FY29E | G3: FY30E
A4: A. REVENUE PROJECTION (INR Mn)
A5: Revenue Growth Rate (YoY) | C5: =Assumptions!B15 -> 0.05 | D5: =Assumptions!B16 -> 0.07 | E5: =Assumptions!B17 -> 0.09 | F5: =Assumptions!B18 -> 0.1 | G5: =Assumptions!B19 -> 0.1
A6: Revenue | B6: 2553240 | C6: =B6*(1+C5) -> 2680902 | D6: =C6*(1+D5) -> 2868565.1 | E6: =D6*(1+E5) -> 3126736 | F6: =E6*(1+F5) -> 3439409.6 | G6: =F6*(1+G5) -> 3783350.6
A7: (FY25A revenue sourced from Q2 FY26 data sheet)
A8: B. EBITDA (INR Mn)
A9: EBITDA Margin (%) | B9: =662540/2553240 -> 0.2594899 | D9: =Assumptions!B20 -> 0.26 | E9: =Assumptions!B20 -> 0.26 | F9: =Assumptions!B20 -> 0.26 | G9: =Assumptions!B20 -> 0.26
A10: EBITDA | B10: 662540 | C10: =C6*C9 -> 0 | D10: =D6*D9 -> 745826.94 | E10: =E6*E9 -> 812951.36 | F10: =F6*F9 -> 894246.5 | G10: =G6*G9 -> 983671.15
A11: C. DEPRECIATION & AMORTISATION
A12: D&A (INR Mn, est. flat ~40-52Bn) | B12: 40890 | C12: 43000 | D12: 45000 | E12: 47000 | F12: 49000 | G12: 51000
A13: EBIT (EBITDA – D&A) | B13: =B10-B12 -> 621650 | C13: =C10-C12 -> -43000 | D13: =D10-D12 -> 700826.94 | E13: =E10-E12 -> 765951.36 | F13: =F10-F12 -> 845246.5 | G13: =G10-G12 -> 932671.15
A14: D. FREE CASH FLOW (FCF) COMPUTATION
A15: Effective Tax Rate | B15: =Assumptions!B22 -> 0.26 | C15: =Assumptions!B22 -> 0.26 | D15: =Assumptions!B22 -> 0.26 | E15: =Assumptions!B22 -> 0.26 | F15: =Assumptions!B22 -> 0.26 | G15: =Assumptions!B22 -> 0.26
A16: NOPAT (EBIT × (1 – Tax Rate)) | B16: =B13*(1-B15) -> 460021 | C16: =C13*(1-C15) -> -31820 | D16: =D13*(1-D15) -> 518611.93 | E16: =E13*(1-E15) -> 566804.01 | F16: =F13*(1-F15) -> 625482.41 | G16: =G13*(1-G15) -> 690176.65
A17: Add: Depreciation & Amortisation | B17: =B12 -> 40890 | C17: =C12 -> 43000 | D17: =D12 -> 45000 | E17: =E12 -> 47000 | F17: =F12 -> 49000 | G17: =G12 -> 51000
A18: Less: Capex (% of Revenue) | B18: =-B6*Assumptions!B21 -> -51064.8 | C18: =-C6*Assumptions!B21 -> -53618.04 | D18: =-D6*Assumptions!B21 -> -57371.303 | E18: =-E6*Assumptions!B21 -> -62534.72 | F18: =-F6*Assumptions!B21 -> -68788.192 | G18: =-G6*Assumptions!B21 -> -75667.011
A19: Less: Change in Working Capital (est.) | B19: 0 | C19: -15000 | D19: -18000 | E19: -20000 | F19: -22000 | G19: -24000
A20: FREE CASH FLOW (FCF) | B20: =B16+B17+B18+B19 -> 449846.2 | C20: =C16+C17+C18+C19 -> -57438.04 | D20: =D16+D17+D18+D19 -> 488240.63 | E20: =E16+E17+E18+E19 -> 531269.29 | F20: =F16+F17+F18+F19 -> 583694.22 | G20: =G16+G17+G18+G19 -> 641509.64
A21: E. DISCOUNTING & TERMINAL VALUE
A22: WACC | B22: =Assumptions!B24 -> 0.105 | C22: =Assumptions!B24 -> 0.105 | D22: =Assumptions!B24 -> 0.105 | E22: =Assumptions!B24 -> 0.105 | F22: =Assumptions!B24 -> 0.105 | G22: =Assumptions!B24 -> 0.105
A23: Year (t) | B23: FY25A | C23: 1 | D23: 2 | E23: 3 | F23: 4 | G23: 5
A24: Discount Factor [1/(1+WACC)^t] | B24: — | C24: =1/(1+C22)^1 -> 0.90497738 | D24: =1/(1+C22)^2 -> 0.81898405 | E24: =1/(1+C22)^3 -> 0.74116204 | F24: =1/(1+C22)^4 -> 0.67073487 | G24: =1/(1+C22)^5 -> 0.60699989
A25: PV of FCF | B25: — | C25: =C20*C24 -> -51980.127 | D25: =D20*D24 -> 399861.29 | E25: =E20*E24 -> 393756.63 | F25: =F20*F24 -> 391504.07 | G25: =G20*G24 -> 389396.28
A26: Terminal Growth Rate (g) | B26: =Assumptions!B23 -> 0.05 | C26: =Assumptions!B23 -> 0.05 | D26: =Assumptions!B23 -> 0.05 | E26: =Assumptions!B23 -> 0.05 | F26: =Assumptions!B23 -> 0.05 | G26: =Assumptions!B23 -> 0.05
A27: Terminal Value [FCF₅ × (1+g) / (WACC − g)] | B27: — | C27: — | D27: — | E27: — | F27: — | G27: =G20*(1+Assumptions!B23)/(Assumptions!B24-Assumptions!B23) -> 12247002
A28: PV of Terminal Value | B28: — | C28: — | D28: — | E28: — | F28: — | G28: =G27*G24 -> 7433928.9
A30: F. INTRINSIC VALUE SUMMARY
A31: Sum of PV(FCFs) – FY26 to FY30 | C31: =SUM(C25:G25) -> 1522538.1
A32: PV of Terminal Value | C32: =G28 -> 7433928.9
A33: Enterprise Value (EV) | C33: =C31+C32 -> 8956467.1
A34: Add: Net Cash & Investments (INR Mn) | C34: =Assumptions!B26 -> 450000
A35: Equity Value | C35: =C33+C34 -> 9406467.1
A36: Shares Outstanding (Mn) | C36: =Assumptions!B25 -> 3618
A38: ➤ DCF INTRINSIC VALUE PER SHARE (INR) | G38: =(C35/Assumptions!B25)*1 -> 2599.908
A39: Current Market Price (INR) — update as needed | G39: 3280
A40: Upside / (Downside) = (DCF Price − Market) / Market | G40: =(G38-G39)/G39 -> -0.20734513

Sheet Sensitivity
A1: SENSITIVITY ANALYSIS – DCF Intrinsic Value per Share (INR)
A2: WACC ↓ / TGR → | B2: 3% | C2: 4% | D2: 5% | E2: 6% | F2: 7%
A3: 8.5% | B3: 1647 | C3: 1929 | D3: 2372 | E3: 3170 | F3: 5032
A4: 9.5% | B4: 1416 | C4: 1604 | D4: 1876 | E4: 2303 | F4: 3072
A5: 10.5% | B5: 1249 | C5: 1382 | D5: 1563 | E5: 1825 | F5: 2237
A6: 11.5% | B6: 1122 | C6: 1221 | D6: 1349 | E6: 1524 | F6: 1777
A7: 12.5% | B7: 1024 | C7: 1099 | D7: 1194 | E7: 1318 | F7: 1487
A9: Note: Sensitivity uses simplified FCF base. See DCF Model sheet for full computation.

Sheet Valuation Bridge
A1: VALUATION BRIDGE & EQUITY RESEARCH SUMMARY
A2: COMPONENT | B2: VALUE (INR Mn) | C2: NOTES
A3: PV of FCFs (FY26E–FY30E) | B3: → see DCF Model | C3: 5-year explicit forecast period
A4: PV of Terminal Value | B4: → see DCF Model | C4: Gordon Growth Model; g=5%, WACC=10.5%
A5: Enterprise Value (EV) | B5: → H column, DCF | C5: Sum of above
A6: + Net Cash & Investments | B6: ~450,000 Mn | C6: Cash, bank deposits, investments (FY25)
A7: Equity Value | B7: → H column, DCF
A8: ÷ Shares Outstanding | B8: 3,618 Mn | C8: As per latest filing
A9: DCF Intrinsic Value / Share | B9: → G column, DCF | C9: Base case
A10: Market Price (CMP) | B10: ~₹3,280 | C10: Approximate, April 2026
A11: Implied Upside / (Downside) | B11: → G column, DCF | C11: (DCF – CMP) / CMP
A13: IMPORTANT DISCLAIMER
A14: This model is for educational/analytical purposes only. It is not investment advice. DCF valuations are highly sensitive to assumptions. Always conduct independent research and consult a SEBI-registered financial advisor before investing.
